dsef/__init__.py
dsef/dsef.py
dsef/dsef_base.py
dsef/dsef_tools.py
dsef/line_tools.py
dsef-0.3.0.dist-info/licenses/LICENSE.txt
tests/__init__.py
tests/test_dsef.py
tests/test_dsef_base.py
tests/test_dsef_tools.py
tests/test_line_tools.py
dsef-0.3.0.dist-info/METADATA
dsef-0.3.0.dist-info/WHEEL
dsef-0.3.0.dist-info/top_level.txt
dsef-0.3.0.dist-info/RECORD
