Metadata-Version: 2.4
Name: dsef
Version: 0.3.0
Summary: Direct Step Edge Detection
Home-page: https://github.com/Autonomi-USN/DSEF
Author: Agnar Sivertsen, Fabio Andrade, Marcos Moura
Author-email: agsi@norceresearch.no, fabio@ieee.org, marcos.moura@usn.no
License: MIT
Keywords: edge,edge detection,edge follower,computer vision,image
Classifier: Development Status :: 3 - Alpha
Classifier: License :: OSI Approved :: MIT License
Classifier: Intended Audience :: Science/Research
Classifier: Programming Language :: Python
Classifier: Topic :: Scientific/Engineering
Classifier: Topic :: Scientific/Engineering :: Artificial Intelligence
Classifier: Topic :: Scientific/Engineering :: Image Processing
Classifier: Topic :: Scientific/Engineering :: Visualization
Classifier: Programming Language :: Python :: 3
Classifier: Programming Language :: Python :: 3.9
Classifier: Programming Language :: Python :: 3.10
Classifier: Programming Language :: Python :: 3.11
Classifier: Programming Language :: Python :: 3.12
Requires-Python: >=3.8
License-File: LICENSE.txt
Dynamic: author
Dynamic: author-email
Dynamic: description
Dynamic: description-content-type
Dynamic: home-page
Dynamic: license
Dynamic: license-file
Dynamic: requires-python
Dynamic: summary
